YandexIOT/SmartHome.py
YandexIOT/__init__.py
YandexIOT/Devices/SmartDevice.py
YandexIOT/Devices/SmartLight.py
YandexIOT/Devices/SmartVacuum.py
YandexIOT/Devices/__init__.py
YandexIOT-0.1.dist-info/LICENSE
YandexIOT-0.1.dist-info/METADATA
YandexIOT-0.1.dist-info/WHEEL
YandexIOT-0.1.dist-info/top_level.txt
YandexIOT-0.1.dist-info/RECORD
