Metadata-Version: 2.1
Name: YandexIOT
Version: 0.1
Summary: Library for controlling Yandex Smart Devices in Python
Home-page: https://github.com/Artingl/YandexIOT
Author: Artingl
Author-email: mikrobamboni@yandex.ru
Project-URL: Bug Tracker, https://github.com/Artingl/YandexIOT/issues
Classifier: Programming Language :: Python :: 3
Classifier: License :: OSI Approved :: Apache Software License
Classifier: Operating System :: OS Independent
Requires-Python: >=3.6
License-File: LICENSE
Requires-Dist: requests (==2.27.1)
